{
    "ndata": 287.7808006347497,
    "start": 0,
    "stop": 150,
    "levels": [
        4.5,
        3.0,
        2.0,
        0.5,
        0.0,
        -0.5,
        -2.0,
        -3.0,
        -4.5
    ],
    "points": [
        [],
        [],
        [],
        [],
        [
            0.0
        ],
        [
            17.298141317014892
        ],
        [
            35.274213540998915
        ],
        [
            43.57649069233262
        ],
        [
            53.935143088642455
        ]
    ]
}