{
    "ndata": 11,
    "start": 0,
    "stop": 40,
    "levels": [
        4.5,
        3.0,
        2.0,
        0.5,
        0.0,
        -0.5,
        -2.0,
        -3.0,
        -4.5
    ],
    "points": [
        [],
        [],
        [],
        [
            1.1653776502842697,
            7.114305791022204
        ],
        [
            0.0,
            8.943806037089844
        ],
        [
            10.3947963827354
        ],
        [
            13.901332975650016
        ],
        [
            15.900197297750827
        ],
        [
            18.634489509682997
        ]
    ]
}