{
    "ndata": 7.061974146122506,
    "start": 0,
    "stop": 20,
    "levels": [
        4.5,
        3.0,
        2.5,
        0.5,
        0.0,
        -0.5,
        -2.5,
        -3.0,
        -4.5
    ],
    "points": [
        [],
        [],
        [],
        [],
        [
            0.0,
            4.991140473065074
        ],
        [
            6.494086342554399
        ],
        [
            10.73627839018669
        ],
        [
            11.629723968666875
        ],
        [
            14.124945828911278
        ]
    ]
}