{
    "ndata": 12.598143771115733,
    "start": 0,
    "stop": 30,
    "levels": [
        4.5,
        3.0,
        2.5,
        0.5,
        0.0,
        -0.5,
        -2.5,
        -3.0,
        -4.5
    ],
    "points": [
        [],
        [],
        [],
        [],
        [
            0.0,
            6.772505961367772
        ],
        [
            8.640236941810473
        ],
        [
            13.782114690591834
        ],
        [
            14.843347996596572
        ],
        [
            17.77519891880286
        ]
    ]
}