{
    "ndata": 0.8986842973625797,
    "start": 0,
    "stop": 15,
    "levels": [
        4.5,
        3.0,
        2.5,
        0.5,
        0.0,
        -0.5,
        -2.5,
        -3.0,
        -4.5
    ],
    "points": [
        [],
        [],
        [],
        [],
        [
            0.0
        ],
        [
            0.7336406050995669
        ],
        [
            3.2554081264729047
        ],
        [
            3.8432417888625685
        ],
        [
            5.55932514094391
        ]
    ]
}