{
    "ndata": 7,
    "start": 0,
    "stop": 20,
    "levels": [
        4.5,
        3.0,
        2.0,
        0.5,
        0.0,
        -0.5,
        -2.0,
        -3.0,
        -4.5
    ],
    "points": [
        [],
        [],
        [],
        [
            0.6672608355834466,
            6.89293259894022
        ],
        [
            0.0,
            8.222216222292005
        ],
        [
            9.36325451437857
        ],
        [
            12.273572707708373
        ],
        [
            13.988454953250523
        ],
        [
            16.37582039400369
        ]
    ]
}