{
    "ndata": 5.853863747902039,
    "start": 0,
    "stop": 25,
    "levels": [
        4.5,
        3.0,
        2.5,
        0.5,
        0.0,
        -0.5,
        -2.5,
        -3.0,
        -4.5
    ],
    "points": [
        [],
        [],
        [],
        [],
        [
            0.0
        ],
        [
            2.763491730509567
        ],
        [
            7.190256924902738
        ],
        [
            8.074018407252469
        ],
        [
            10.521819260912267
        ]
    ]
}